django_bench_runner/__init__.py
django_bench_runner/runner.py
django_bench_runner/tabulate.py
django_bench_runner-0.1.1.dist-info/DESCRIPTION.rst
django_bench_runner-0.1.1.dist-info/METADATA
django_bench_runner-0.1.1.dist-info/RECORD
django_bench_runner-0.1.1.dist-info/WHEEL
django_bench_runner-0.1.1.dist-info/metadata.json
django_bench_runner-0.1.1.dist-info/top_level.txt
