Metadata-Version: 2.0
Name: django-bench-runner
Version: 0.1.1
Summary: Locate slow tests in your django project.
Home-page: http://github.com/scuml/django_bench_runner
Author: Stephen Mitchell
Author-email: stephen@echodot.com
License: Copyright 2016 Stephen Mitchell
